baobao/License.md
baobao/__init__.py
baobao/pipeline.py
baobao/utils/__init__.py
baobao/utils/examples.py
baobao/utils/print_pipeline.py
baobao/utils/run_parallel.py
baobao-0.2.4.dist-info/WHEEL
baobao-0.2.4.dist-info/METADATA
baobao-0.2.4.dist-info/RECORD
