Metadata-Version: 2.1
Name: baobao
Version: 0.2.4
Summary: 
Home-page: https://hollstein.github.io/baobao/
License: MIT
Author: André Hollstein
Author-email: andre@dr-hollstein.de
Requires-Python: >=3.8,<4.0
Classifier: License :: OSI Approved :: MIT License
Classifier: Programming Language :: Python :: 3
Classifier: Programming Language :: Python :: 3.8
Project-URL: Documentation, https://hollstein.github.io/baobao/
Project-URL: Repository, https://github.com/hollstein/baobao
